pygv/__init__.py
pygv/_api.py
pygv/_browser.py
pygv/_config.py
pygv/_tracks.py
pygv/_version.py
pygv/static/widget.js
pygv-0.2.2.dist-info/METADATA
pygv-0.2.2.dist-info/WHEEL
pygv-0.2.2.dist-info/licenses/LICENSE
pygv-0.2.2.dist-info/RECORD
