Metadata-Version: 2.4
Name: pygv
Version: 0.2.2
License-File: LICENSE
Requires-Python: >=3.9
Requires-Dist: anywidget>=0.9.3
Requires-Dist: msgspec>=0.18.6
Requires-Dist: servir>=0.2.1
